{
  "format_version": "1.18.3",
  "minecraft:client_entity": {
    "description": {
      "identifier": "pokemon:ironvaliant",
      "materials": {
        "default": "entity_emissive_alpha",
        "aura": "charged_creeper"
      },
      "textures": {
        "evo_aura": "textures/entity/evolving",
        "default": "textures/entity/pokemon/ironvaliant/ironvaliant.png",
        "shiny_default": "textures/entity/pokemon/ironvaliant/shiny_ironvaliant.png"
      },
      "scripts": {
        "animate": [
          "controller",
          {
            "blink": "math.random(0.0, 25.0) <= 0.25"
          }
        ]
      },
      "animations": {
        "blink": "animation.ironvaliant.blink",
        "ground_idle": "animation.ironvaliant.ground_idle",
        "air_idle": "animation.ironvaliant.ground_idle",
        "water_idle": "animation.ironvaliant.water_idle",
        "walking": "animation.ironvaliant.walking",
        "flying": "animation.ironvaliant.ground_idle",
        "swimming": "animation.ironvaliant.swimming",
        "sleeping": "animation.ironvaliant.sleeping",
        "attack": "animation.ironvaliant.attack",
        "look_at_target": "animation.pokemon.look_at_target",
        "controller": "controller.animation.pokemon"
      },
      "render_controllers": [
        {
          "controller.render.pokemon": "query.variant==0"
        },
        {
          "controller.render.evolve": "query.variant==1"
        }
      ],
      "spawn_egg": {
        "texture": "ironvaliant",
        "texture_index": 0
      },
      "geometry": {
        "default": "geometry.ironvaliant"
      }
    }
  }
}
