{
	"format_version": "1.18.3",
	"minecraft:client_entity": {
		"description": {
			"identifier": "pokemon:meowthgmax",
			"materials": {
				"default": "zombie"
			},
			"textures": {
				"default": "textures/sprites/default/meowthgmax",
				"shiny_default": "textures/sprites/default/meowthgmax",
				"default_male": "textures/sprites/default/meowthgmax",
				"default_female": "textures/sprites/default/meowthgmax",
				"shiny_male": "textures/sprites/default/meowthgmax",
				"shiny_female": "textures/sprites/default/meowthgmax"
			},
			"geometry": {
				"default": "geometry.substitute"
			},
			"render_controllers": [
				"controller.render.pokemon"
			],
			"spawn_egg": {
				"texture": "meowthgmax",
				"texture_index": 0
			}
		}
	}
}
