{
    "format_version": "1.18.3",
    "minecraft:client_entity": {
        "description": {
            "identifier": "pokemon:mrmimegalar",
            "materials": {
                "default": "zombie"
            },
            "textures": {
                "default": "textures/sprites/mrmimegalar",
                "shiny": "textures/sprites/mrmimegalar",
                "default_male": "textures/sprites/mrmimegalar",
                "default_female": "textures/sprites/mrmimegalar",
                "shiny_male": "textures/sprites/mrmimegalar",
                "shiny_female": "textures/sprites/mrmimegalar",
                "halloween": "textures/sprites/mrmimegalar",
                "shiny_halloween": "textures/sprites/mrmimegalar",
                "doll_female": "textures/sprites/mrmimegalar",
                "doll_male": "textures/sprites/mrmimegalar",
                "witch_female": "textures/sprites/mrmimegalar",
                "witch_male": "textures/sprites/mrmimegalar",
                "cap_female": "textures/sprites/mrmimegalar",
                "cap_male": "textures/sprites/mrmimegalar",
                "santa_female": "textures/sprites/mrmimegalar",
                "santa_male": "textures/sprites/mrmimegalar",
                "tophat_female": "textures/sprites/mrmimegalar",
                "tophat_male": "textures/sprites/mrmimegalar",
                "tophat_stpatricks_female": "textures/sprites/mrmimegalar",
                "tophat_stpatricks_male": "textures/sprites/mrmimegalar",
                "tophat_4thjuly_female": "textures/sprites/mrmimegalar",
                "tophat_4thjuly_male": "textures/sprites/mrmimegalar",
                "detective": "textures/sprites/mrmimegalar"
            },
            "geometry": {
                "default": "geometry.substitute"
            },
            "render_controllers": [
                "controller.render.pokemon"
            ],
            "spawn_egg": {
                "texture": "mrmimegalar",
                "texture_index": 0
            }
        }
    }
}