{
    "format_version": "1.18.3",
    "minecraft:client_entity": {
        "description": {
            "identifier": "pokemon:pineco",
            "materials": {
                "default": "zombie"
            },
            "textures": {
                "default": "textures/entity/pokemon/pineco/pineco",
                "shiny": "textures/entity/pokemon/pineco/shiny_pineco"
            },
            "geometry": {
                "default": "geometry.pineco"
            },
            "scripts": {
                "animate": [
                    "look_at_target",
                    "ground_pokemon"
                ]
            },
            "animations": {
                "walk": "animation.pineco.walk",
                "look_at_target": "animation.common.look_at_target",
                "chill": "animation.pineco.chill",
                "flying_pokemon": "controller.animation.flying.pokemon",
                "ground_pokemon": "controller.animation.ground.pokemon"
            },
            "render_controllers": [
                "controller.render.pokemon"
            ],
            "spawn_egg": {
                "texture": "pineco",
                "texture_index": 0
            }
        }
    }
}