{
	"format_version": "1.8.0",
	"animations": {
		"animation.melmetal.idle": {
			"loop": true,
			"animation_length": 2,
			"override_previous_animation": true,
			"anim_time_update": "2.0s",
			"bones": {
				"bot_torso": {
					"rotation": {
						"0.0": {
							"post": [0, 5, 0],
							"lerp_mode": "catmullrom"
						},
						"0.5": {
							"post": [0, -5, 0],
							"lerp_mode": "catmullrom"
						},
						"1.0": {
							"post": [0, -5, 0],
							"lerp_mode": "catmullrom"
						},
						"1.5": {
							"post": [0, 0, 0],
							"lerp_mode": "catmullrom"
						},
						"2.0": {
							"post": [0, 0, 0],
							"lerp_mode": "catmullrom"
						}
					}
				}
			}
		},
		"animation.melmetal.walk": {
			"loop": true,
			"animation_length": 2,
			"anim_time_update": 0.1,
			"bones": {
				"arm_l_4": {
					"rotation": {
						"0.0": {
							"post": [0, 30, 0],
							"lerp_mode": "catmullrom"
						},
						"0.8333": {
							"post": [0, -30, 0],
							"lerp_mode": "catmullrom"
						},
						"1.6667": {
							"post": [0, 30, 0],
							"lerp_mode": "catmullrom"
						}
					}
				},
				"arm_l_2": {
					"rotation": {
						"0.0": {
							"post": [0, 30, 0],
							"lerp_mode": "catmullrom"
						},
						"1.0": {
							"post": [0, -30, 0],
							"lerp_mode": "catmullrom"
						},
						"2.0": {
							"post": [0, 30, 0],
							"lerp_mode": "catmullrom"
						}
					}
				},
				"leg_left_top": {
					"rotation": {
						"0.0": {
							"post": [30, 0, 0],
							"lerp_mode": "catmullrom"
						},
						"1.0": {
							"post": [-30, 0, 0],
							"lerp_mode": "catmullrom"
						},
						"2.0": {
							"post": [30, 0, 0],
							"lerp_mode": "catmullrom"
						}
					}
				},
				"leg_right_top": {
					"rotation": {
						"0.0": {
							"post": [-30, 0, 0],
							"lerp_mode": "catmullrom"
						},
						"1.0": {
							"post": [30, 0, 0],
							"lerp_mode": "catmullrom"
						},
						"2.0": {
							"post": [-30, 0, 0],
							"lerp_mode": "catmullrom"
						}
					}
				}
			}
		},
		"animation.melmetal.attack": {
			"animation_length": 0.753,
			"bones": {
				"top_torso": {
					"rotation": {
						"0.0": {
							"post": [0, 0, 0],
							"lerp_mode": "catmullrom"
						},
						"0.3125": {
							"post": [8, 0, 0],
							"lerp_mode": "catmullrom"
						},
						"0.75": {
							"post": [0, 0, 0],
							"lerp_mode": "catmullrom"
						}
					}
				},
				"right_arm": {
					"rotation": {
						"0.0": {
							"post": [0, 0, 0],
							"lerp_mode": "catmullrom"
						},
						"0.3125": {
							"post": [0, -30, 0],
							"lerp_mode": "catmullrom"
						},
						"0.75": {
							"post": [0, 0, 0],
							"lerp_mode": "catmullrom"
						}
					}
				},
				"arm_l_4": {
					"rotation": {
						"0.0": {
							"post": [0, 0, 0],
							"lerp_mode": "catmullrom"
						},
						"0.3125": {
							"post": [0, 0, 30],
							"lerp_mode": "catmullrom"
						},
						"0.75": {
							"post": [0, 0, 0],
							"lerp_mode": "catmullrom"
						}
					}
				},
				"bone2": {
					"rotation": {
						"0.0": [0, 0, 0],
						"0.3125": [0, -30, 0],
						"0.75": [0, 0, 0]
					}
				},
				"bone5": {
					"rotation": {
						"0.0": [0, 0, 0],
						"0.3125": [-30, 0, 0],
						"0.75": [0, 0, 0]
					}
				},
				"left_arm": {
					"rotation": {
						"0.0": {
							"post": [0, 0, 0],
							"lerp_mode": "catmullrom"
						},
						"0.3125": {
							"post": [0, -10, 0],
							"lerp_mode": "catmullrom"
						},
						"0.75": {
							"post": [0, 0, 0],
							"lerp_mode": "catmullrom"
						}
					}
				},
				"bone": {
					"rotation": {
						"0.0": [0, 0, 0],
						"0.3125": [0, -20, 0],
						"0.75": [0, 0, 0]
					}
				},
				"bone8": {
					"rotation": {
						"0.0": [0, 0, 0],
						"0.3125": [0, 30, 0],
						"0.75": [0, 0, 0]
					}
				}
			}
		}
	}
}