{
	"format_version": "1.8.0",
	"animations": {
		"animation.sunflora.ground_idle": {
			"loop": true,
			"animation_length": 4,
			"bones": {
				"RightArm": {
					"rotation": [0, "-15+Math.cos((query.anim_time) *90-90)*-3", "0+Math.cos((query.anim_time) *90*2-0)*3"]
				},
				"RightForearm": {
					"rotation": [0, 0, "10+Math.cos((query.anim_time) *90*2+60)*3"]
				},
				"LeftArm": {
					"rotation": [0, "15+Math.cos((query.anim_time) *90-90)*3", "0+Math.cos((query.anim_time) *90*2-0)*-3"]
				},
				"LeftForearm": {
					"rotation": [0, 0, "-10+Math.cos((query.anim_time) *90*2+60)*-3"]
				},
				"Head": {
					"rotation": [0, 0, "0+Math.cos((query.anim_time) *90-210)*-3"]
				},
				"body": {
					"rotation": ["0+Math.cos((query.anim_time) *90*2-30)*-2", 0, "0+Math.cos((query.anim_time) *90-90)*-2"],
					"position": [0, "0+Math.cos((query.anim_time) *90*2-90)*-0.1", 0]
				}
			}
		},
		"animation.sunflora.blink": {
			"animation_length": 0.25,
			"bones": {
				"bone": {
					"position": {
						"0.0": [0, 0, 0],
						"0.0417": [0, -0.4, 0],
						"0.1667": [0, -0.4, 0],
						"0.2083": [0, 0, 0]
					},
					"scale": {
						"0.0": [1, 1, 1],
						"0.0417": [1, 0.1, 1],
						"0.1667": [1, 0.1, 1],
						"0.2083": [1, 1, 1]
					}
				}
			}
		},
		"animation.sunflora.walking": {
			"loop": true,
			"animation_length": 2,
			"bones": {
				"Sunflora": {
					"rotation": [5, 0, "0+Math.cos((query.anim_time) *90*2-30)*-3"],
					"position": [0, "0+Math.cos((query.anim_time) *90*4-90)*-0.1", 0]
				},
				"RightLeg": {
					"rotation": ["0+Math.cos((query.anim_time) *90*2-30)*20", "-30+Math.cos((query.anim_time) *90*2-90)*20", 0],
					"position": [0, "0.5+Math.cos((query.anim_time) *90*2-120)*0.5", 0]
				},
				"LeftLeg": {
					"rotation": ["0+Math.cos((query.anim_time) *90*2-30)*-20", "30+Math.cos((query.anim_time) *90*2-90)*20", 0],
					"position": [0, "0.5+Math.cos((query.anim_time) *90*2-120)*-0.5", 0]
				},
				"RightArm": {
					"rotation": [0, "0+Math.cos((query.anim_time) *90*2-30)*-10", "10+Math.cos((query.anim_time) *90*4-180)*-3"]
				},
				"RightForearm": {
					"rotation": [0, 0, "10+Math.cos((query.anim_time) *90*4-240)*-3"]
				},
				"LeftArm": {
					"rotation": [0, "0+Math.cos((query.anim_time) *90*2-30)*-10", "-10+Math.cos((query.anim_time) *90*4-180)*3"]
				},
				"LeftForearm": {
					"rotation": [0, 0, "-10+Math.cos((query.anim_time) *90*4-240)*3"]
				},
				"Head": {
					"rotation": ["0+Math.cos((query.anim_time) *90*4-30)*-3", "0+Math.cos((query.anim_time) *90*2-90)*-5", "0+Math.cos((query.anim_time) *90*2-30)*-3"]
				},
				"body": {
					"rotation": [0, "0+Math.cos((query.anim_time) *90*2-60)*5", "0+Math.cos((query.anim_time) *90*2-0)*5"]
				}
			}
		},
		"animation.sunflora.attack": {
			"loop": true,
			"animation_length": 3,
			"bones": {
				"Sunflora": {
					"position": {
						"0.0": [0, 0, 0],
						"0.875": [0, 0, 0],
						"1.0": [0, 2, 0],
						"1.125": [0, 2.2, 0],
						"1.25": [0, 2, 0],
						"1.375": [0, 0, 0],
						"1.5": [0, -0.2, 0],
						"1.625": [0, 0, 0]
					}
				},
				"RightLeg": {
					"rotation": {
						"0.0": [0, 0, 0],
						"0.25": [0, -20, 0],
						"0.375": [0, -30, 0],
						"0.5": [0, -35, 0],
						"0.875": [0, -35, 0],
						"1.0": [33.08878, -25.89816, -43.48302],
						"1.125": [36.77809, -23.03233, -48.99626],
						"1.25": [36.78, -23.03, -49],
						"1.375": [0, -35, 0],
						"2.0": [0, -35, 0],
						"2.125": [0, -30.25, 0],
						"2.375": [0, -10.08, 0],
						"2.5": [0, -2, 0],
						"2.625": [0, 0, 0]
					}
				},
				"LeftLeg": {
					"rotation": {
						"0.0": [0, 0, 0],
						"0.25": [0, 20, 0],
						"0.375": [0, 30, 0],
						"0.5": [0, 35, 0],
						"0.875": [0, 35, 0],
						"1.0": [33.08878, 25.89816, 43.48302],
						"1.125": [36.77809, 23.03233, 48.99626],
						"1.25": [38.42857, 21.50418, 51.57675],
						"1.375": [0, 35, 0],
						"2.125": [0, 35, 0],
						"2.25": [0, 32.25, 0],
						"2.5": [0, 9.42, 0],
						"2.625": [0, 4, 0],
						"2.75": [0, 0, 0]
					}
				},
				"RightArm": {
					"rotation": {
						"0.0": [0, 0, 10],
						"0.125": [0, 2.5, 10],
						"0.375": [0, -20, 10],
						"0.5": [0, -25, 10],
						"0.625": [0, -27.5, 10],
						"0.75": [0, -27.5, 10],
						"1.0": [0, 10, 20],
						"1.125": [0, 15, 25],
						"1.25": [0, 20, 20],
						"1.3333": [0, 20, 10],
						"1.5": [-27.47, -39.18, 43.83],
						"1.625": [-48.06989, -41.56076, 69.21027],
						"1.75": [-49.79019, -43.20355, 71.76186],
						"2.0": [-46.44198, -46.92513, 67.03418],
						"2.25": [-23.22, -35.46, 38.52],
						"2.5": [0, -8, 10],
						"2.625": [0, 0, 10]
					}
				},
				"RightForearm": {
					"rotation": [0, 0, 10]
				},
				"LeftArm": {
					"rotation": {
						"0.0": [0, 0, -10],
						"0.125": [0, -2.5, -10],
						"0.375": [0, 20, -10],
						"0.5": [0, 25, -10],
						"0.5417": [0, 26.22, -10],
						"0.625": [0, 27.5, -10],
						"0.75": [0, 27.5, -10],
						"1.0": [0, -10, -20],
						"1.125": [0, -15, -25],
						"1.25": [0, -20, -20],
						"1.3333": [0, -20, -10],
						"1.5": [-27.47, 38.18, -43.83],
						"1.625": [-48.06989, 41.56076, -69.21027],
						"1.75": [-49.79019, 43.20355, -71.76186],
						"2.0": [-46.44198, 46.92513, -67.03418],
						"2.25": [-27.87, 32.16, -44.22],
						"2.5": [-9.29, 10.05, -21.41],
						"2.625": [0, 0, -10]
					}
				},
				"LeftForearm": {
					"rotation": [0, 0, -10]
				},
				"Head": {
					"rotation": {
						"0.0": [0, 0, 0],
						"0.25": [0, 0, 0],
						"0.5": [5, 0, 0],
						"0.625": [7.5, 0, 0],
						"0.75": [8.5, 0, 0],
						"0.875": [7.5, 0, 0],
						"1.125": [0, 0, 0],
						"1.25": [-6.5, 0, 0],
						"1.375": [-7.5, 0, 0],
						"1.5": [25, 0, 0],
						"1.625": [30.5, 0, 0],
						"1.75": [30, 0, 0],
						"1.875": [26.5, 0, 0],
						"2.0": [13.17, 0, 0],
						"2.125": [3.83, 0, 0],
						"2.25": [0, 0, 0]
					}
				},
				"body": {
					"rotation": {
						"0.0": [0, 0, 0],
						"0.25": [7.5, 0, 0],
						"0.375": [10, 0, 0],
						"0.5": [11, 0, 0],
						"0.625": [10, 0, 0],
						"0.75": [3, 0, 0],
						"0.875": [-16.5, 0, 0],
						"1.0": [-32, 0, 0],
						"1.125": [-34.5, 0, 0],
						"1.25": [-34.5, 0, 0],
						"1.2917": [8, 0, 0],
						"1.375": [48, 0, 0],
						"1.5": [60.5, 0, 0],
						"1.625": [62.7, 0, 0],
						"1.75": [60.5, 0, 0],
						"2.0": [49.25, 0, 0],
						"2.5": [5, 0, 0],
						"2.625": [2, 0, 0],
						"2.875": [0, 0, 0]
					}
				}
			}
		},
		"animation.sunflora.sleeping": {
			"loop": true,
			"animation_length": 2,
			"bones": {
				"Sunflora": {
					"position": [0, -3, 0]
				},
				"RightLeg": {
					"rotation": [-76.72537, -2.00645, 85.49568]
				},
				"LeftLeg": {
					"rotation": [-76.72537, 2.00645, -85.49568]
				},
				"RightArm": {
					"rotation": [0, 0, "-50+Math.cos((query.anim_time) *90*2-90)*1"],
					"position": [0, 0, 0]
				},
				"RightForearm": {
					"rotation": [0, 0, 25]
				},
				"LeftArm": {
					"rotation": [0, 0, "50+Math.cos((query.anim_time) *90*2-90)*-1"]
				},
				"LeftForearm": {
					"rotation": [0, 0, -25]
				},
				"Head": {
					"rotation": ["35+Math.cos((query.anim_time) *90*2-90)*-1", 0, 0]
				},
				"body": {
					"rotation": ["0+Math.cos((query.anim_time) *90*2-30)*-1", 0, 0],
					"position": [0, "0+Math.cos((query.anim_time) *90*2-90)*-0.05", 0]
				}
			}
		},
		"animation.sunflora.water_idle": {
			"loop": true,
			"animation_length": 2,
			"bones": {
				"Sunflora": {
					"position": [0, "-8+Math.cos((query.anim_time) *90*2-30)*-0.5", 0]
				},
				"RightLeg": {
					"rotation": [-45.25595, -22.74635, "57.3674+Math.cos((query.anim_time) *90*2-90)*-5"]
				},
				"LeftLeg": {
					"rotation": [-45.25595, 22.74635, "-57.3674+Math.cos((query.anim_time) *90*2-90)*5"]
				},
				"RightArm": {
					"rotation": [0, "0+Math.cos((query.anim_time) *90*2-120)*-10", "0+Math.cos((query.anim_time) *90*2-30)*3"]
				},
				"RightForearm": {
					"rotation": [0, "0+Math.cos((query.anim_time) *90*2-180)*-10", 0]
				},
				"LeftArm": {
					"rotation": [0, "0+Math.cos((query.anim_time) *90*2-120)*10", "0+Math.cos((query.anim_time) *90*2-30)*-3"]
				},
				"LeftForearm": {
					"rotation": [0, "0+Math.cos((query.anim_time) *90*2-180)*10", 0]
				},
				"Head": {
					"rotation": ["0+Math.cos((query.anim_time) *90*2-30)*-3", 0, 0]
				},
				"body": {
					"rotation": ["0+Math.cos((query.anim_time) *90*2-90)*-1", 0, 0]
				}
			}
		},
		"animation.sunflora.swimming": {
			"loop": true,
			"animation_length": 2,
			"bones": {
				"Sunflora": {
					"rotation": ["60+Math.cos((query.anim_time) *90*2-90)*-2", 0, 0],
					"position": [0, -4, 5]
				},
				"RightLeg": {
					"rotation": ["0+Math.cos((query.anim_time) *90*2-90)*5", 0, "0+Math.cos((query.anim_time) *90*2-30)*-10 "]
				},
				"LeftLeg": {
					"rotation": ["0+Math.cos((query.anim_time) *90*2-90)*5", 0, "0+Math.cos((query.anim_time) *90*2-30)*10"]
				},
				"RightArm": {
					"rotation": [0, 0, "-15+Math.cos((query.anim_time) *90*2-150)*15"]
				},
				"RightForearm": {
					"rotation": [0, 0, "0+Math.cos((query.anim_time) *90*2-180)*5"]
				},
				"LeftArm": {
					"rotation": [0, 0, "15+Math.cos((query.anim_time) *90*2-150)*-15"]
				},
				"LeftForearm": {
					"rotation": [0, 0, "0+Math.cos((query.anim_time) *90*2-180)*-5"]
				},
				"Head": {
					"rotation": ["-30+Math.cos((query.anim_time) *90*2-30)*-3", 0, 0]
				},
				"body": {
					"rotation": ["0+Math.cos((query.anim_time) *90*2-30)*-1", 0, 0]
				}
			}
		}
	}
}